{
  "id" : "eKTNN78gFdMMq4ofPsJoTHm0JJZkqBwwsQaE8QjjDShg3",
  "birthDate" : "1971-12-20",
  "resourceType" : "Patient",
  "active" : true,
  "telecom" : [
    {
      "use" : "home",
      "system" : "phone",
      "value" : "816-810-5685",
      "rank" : 1
    },
    {
      "system" : "email",
      "value" : "johnbreau@gmail.com",
      "rank" : 1
    }
  ],
  "contact" : [
    {
      "telecom" : [
        {
          "system" : "phone",
          "value" : "816-522-3100",
          "use" : "home"
        },
        {
          "system" : "phone",
          "value" : "816-522-3100",
          "use" : "mobile"
        }
      ],
      "relationship" : [
        {
          "text" : "Spouse",
          "coding" : [
            {
              "system" : "urn:oid:1.2.840.114350.1.13.451.2.7.4.827665.1000",
              "display" : "Spouse",
              "code" : "17"
            }
          ]
        }
      ],
      "name" : {
        "use" : "usual",
        "text" : "Singleton,Catherine"
      },
      "address" : {
        "use" : "home",
        "city" : "Overland Park",
        "district" : "JOHNSON",
        "postalCode" : "66221",
        "country" : "USA",
        "line" : [
          "17225 Nieman Rd"
        ],
        "state" : "KS"
      }
    }
  ],
  "deceasedBoolean" : false,
  "maritalStatus" : {
    "text" : "Married"
  },
  "address" : [
    {
      "use" : "home",
      "city" : "Overland Park",
      "district" : "JOHNSON",
      "postalCode" : "66221-7121",
      "country" : "USA",
      "line" : [
        "17225 Nieman Rd"
      ],
      "state" : "KS"
    },
    {
      "use" : "old",
      "city" : "OVERLAND PARK",
      "district" : "JOHNSON",
      "postalCode" : "66221",
      "country" : "USA",
      "line" : [
        "17225 Nieman Rd"
      ],
      "state" : "KS"
    }
  ],
  "communication" : [
    {
      "preferred" : true,
      "language" : {
        "text" : "English",
        "coding" : [
          {
            "system" : "urn:ietf:bcp:47",
            "display" : "English",
            "code" : "en"
          }
        ]
      }
    }
  ],
  "extension" : [
    {
      "valueCodeableConcept" : {
        "coding" : [
          {
            "system" : "urn:oid:1.2.840.114350.1.13.451.2.7.10.698084.130.657370.6091992199",
            "display" : "male",
            "code" : "male"
          }
        ]
      },
      "url" : "http://open.epic.com/FHIR/StructureDefinition/extension/legal-sex"
    },
    {
      "valueCodeableConcept" : {
        "coding" : [
          {
            "system" : "http://hl7.org/fhir/gender-identity",
            "display" : "male",
            "code" : "male"
          }
        ]
      },
      "url" : "http://hl7.org/fhir/StructureDefinition/patient-genderIdentity"
    },
    {
      "url" : "http://hl7.org/fhir/us/core/StructureDefinition/us-core-birthsex",
      "valueCode" : "M"
    },
    {
      "url" : "http://hl7.org/fhir/us/core/StructureDefinition/us-core-race",
      "extension" : [
        {
          "valueCoding" : {
            "system" : "urn:oid:2.16.840.1.113883.6.238",
            "display" : "White",
            "code" : "2106-3"
          },
          "url" : "ombCategory"
        },
        {
          "valueString" : "White",
          "url" : "text"
        }
      ]
    },
    {
      "url" : "http://hl7.org/fhir/us/core/StructureDefinition/us-core-ethnicity",
      "extension" : [
        {
          "valueCoding" : {
            "system" : "urn:oid:2.16.840.1.113883.6.238",
            "display" : "Not Hispanic or Latino",
            "code" : "2186-5"
          },
          "url" : "ombCategory"
        },
        {
          "valueString" : "Not Hispanic or Latino",
          "url" : "text"
        }
      ]
    },
    {
      "url" : "http://hl7.org/fhir/us/core/StructureDefinition/us-core-sex",
      "valueCode" : "184115007"
    }
  ],
  "managingOrganization" : {
    "display" : "Mayo Clinic",
    "reference" : "Organization/eKBUMPNkVMW0zMCoRDL7cbw3"
  },
  "name" : [
    {
      "use" : "official",
      "text" : "John A Breau",
      "family" : "Breau",
      "given" : [
        "John",
        "A"
      ]
    },
    {
      "use" : "usual",
      "text" : "John A Breau",
      "family" : "Breau",
      "given" : [
        "John",
        "A"
      ]
    }
  ],
  "gender" : "male"
}